nhpp/__init__.py
nhpp/nhpp.py
nhpp-0.0.3.dist-info/LICENSE
nhpp-0.0.3.dist-info/METADATA
nhpp-0.0.3.dist-info/WHEEL
nhpp-0.0.3.dist-info/top_level.txt
nhpp-0.0.3.dist-info/RECORD
