Metadata-Version: 2.1
Name: nhpp
Version: 0.0.3
Summary: Small package to enable creation of Non-homogeneous Poisson Processes.
Home-page: https://github.com/Kylexi/nhpp
Author: Matthew Campbell
Author-email: mmcampbell0@gmail.com
License: UNKNOWN
Platform: UNKNOWN
Classifier: Programming Language :: Python :: 3
Classifier: License :: OSI Approved :: MIT License
Classifier: Operating System :: OS Independent
Requires-Python: >=3.6
Requires-Dist: numpy
